{
    "o:label": "Note",
    "o:resource_template_property": [
        {
            "o:alternate_label": null,
            "o:alternate_comment": null,
            "o:is_required": false,
            "o:is_private": false,
            "o:default_lang": null,
            "data_types": [],
            "vocabulary_namespace_uri": "http:\/\/www.exam.univ-paris8.fr\/onto\/exam#",
            "vocabulary_label": "Gestion des Evaluations",
            "local_name": "valeurNote",
            "label": "valeur de la note"
        },
        {
            "o:alternate_label": null,
            "o:alternate_comment": null,
            "o:is_required": false,
            "o:is_private": false,
            "o:default_lang": null,
            "data_types": [],
            "vocabulary_namespace_uri": "http:\/\/www.exam.univ-paris8.fr\/onto\/exam#",
            "vocabulary_label": "Gestion des Evaluations",
            "local_name": "commentaire",
            "label": "commentaire"
        },
        {
            "o:alternate_label": null,
            "o:alternate_comment": null,
            "o:is_required": false,
            "o:is_private": false,
            "o:default_lang": null,
            "data_types": [],
            "vocabulary_namespace_uri": "http:\/\/www.exam.univ-paris8.fr\/onto\/exam#",
            "vocabulary_label": "Gestion des Evaluations",
            "local_name": "pourEvaluation",
            "label": "pour \u00e9valuation"
        }
    ],
    "o:resource_class": {
        "vocabulary_namespace_uri": "http:\/\/www.exam.univ-paris8.fr\/onto\/exam#",
        "vocabulary_label": "Gestion des Evaluations",
        "local_name": "Note",
        "label": "Note"
    }
}